ig_api/__init__.py
ig_api/_config.py
ig_api/abstract_session.py
ig_api/exceptions.py
ig_api/ig_session.py
ig_api/markets.py
ig_api/price_history_limitation.py
ig_api/data_model/__init__.py
ig_api/data_model/acc_detail.py
ig_api/data_model/instrument.py
ig_api/data_model/market_data.py
ig_api/data_model/order.py
ig_api/data_model/position.py
ig_api/data_model/snapshot.py
ig_api/datasets/__init__.py
ig_api/datasets/historical.py
ig_api/datasets/market_history.py
ig_api/datasets/resolutions.py
ig_api/datasets/synthetic/__init__.py
ig_api/datasets/synthetic/fade_over.py
ig_api/datasets/synthetic/random_slice.py
ig_api/robotrader/__init__.py
ig_api/robotrader/robotrader.py
ig_api/robotrader/features/__init__.py
ig_api/robotrader/features/derived_features.py
ig_api/robotrader/features/features.py
ig_api/robotrader/traders/__init__.py
ig_api/robotrader/traders/evo_trader.py
ig_api/robotrader/traders/evopot.py
ig_api/robotrader/traders/exp_avg.py
ig_api/robotrader/traders/max_short.py
ig_api/robotrader/traders/potential_trader.py
ig_api/robotrader/traders/random.py
ig_api/robotrader/traders/smart_short.py
ig_api/robotrader/visualize/__init__.py
ig_api/robotrader/visualize/visualize_feature.py
ig_api/sim/__init__.py
ig_api/sim/_sim_account.py
ig_api/sim/_sim_market_data.py
ig_api/sim/sim_session.py
ig_api/trading_api/__init__.py
ig_api/trading_api/abstract_session.py
ig_api/trading_api/exceptions.py
ig_api/trading_api/data_model/__init__.py
ig_api/trading_api/data_model/acc_detail.py
ig_api/trading_api/data_model/market_data.py
ig_api/trading_api/data_model/order.py
ig_api/trading_api/data_model/position.py
ig_api/trading_api/data_model/snapshot.py
ig_api/trading_api/ig/__init__.py
ig_api/trading_api/ig/ig_session.py
ig_api/trading_api/ig/price_history_limitation.py
ig_api/trading_api/sim/__init__.py
ig_api/trading_api/sim/_sim_account.py
ig_api/trading_api/sim/_sim_market_data.py
ig_api/trading_api/sim/sim_session.py
robotrader/__init__.py
robotrader/robotrader.py
ig_api-0.11.dist-info/METADATA
ig_api-0.11.dist-info/WHEEL
ig_api-0.11.dist-info/top_level.txt
ig_api-0.11.dist-info/RECORD
